vizchain/__init__.py
vizchain/core.py
vizchain-0.1.1.dist-info/LICENSE
vizchain-0.1.1.dist-info/METADATA
vizchain-0.1.1.dist-info/WHEEL
vizchain-0.1.1.dist-info/top_level.txt
vizchain-0.1.1.dist-info/RECORD
