Metadata-Version: 2.1
Name: vizchain
Version: 0.1.1
Summary: A tiny language interpreter
License-File: LICENSE
Requires-Dist: aiohttp ==3.8.6
Requires-Dist: aiosignal ==1.3.1
Requires-Dist: async-timeout ==4.0.3
Requires-Dist: attrs ==23.1.0
Requires-Dist: certifi ==2023.7.22
Requires-Dist: charset-normalizer ==3.3.0
Requires-Dist: frozenlist ==1.4.0
Requires-Dist: idna ==3.4
Requires-Dist: multidict ==6.0.4
Requires-Dist: openai ==0.28.1
Requires-Dist: requests ==2.31.0
Requires-Dist: tqdm ==4.66.1
Requires-Dist: urllib3 ==2.0.6
Requires-Dist: yarl ==1.9.2
